rsclf/__init__.py
rsclf/model_architecture.py
rsclf/plot.py
rsclf/rawdataset.py
rsclf/test.py
rsclf/train.py
rsclf/wav2feat.py
raw_speech_classification-1.0.4.dist-info/entry_points.txt
raw_speech_classification-1.0.4.dist-info/licenses/LICENSES/GPL-3.0-only.txt
raw_speech_classification-1.0.4.dist-info/WHEEL
raw_speech_classification-1.0.4.dist-info/METADATA
raw_speech_classification-1.0.4.dist-info/RECORD
