Metadata-Version: 2.4
Name: raw-speech-classification
Version: 1.0.4
Summary: Trains CNN classifiers from raw speech using Keras and tests them.
Author: S. Pavankumar Dubagunta, Dr. Mathew Magimai-Doss
Maintainer-email: Olivier Canévet <olivier.canevet@idiap.ch>, Philip Abbet <philip.abbet@idiap.ch>, Yannick Dayer <yannick.dayer@idiap.ch>
Requires-Python: >=3.11
Classifier: License :: OSI Approved :: GNU General Public License v3 (GPLv3)
Classifier: Programming Language :: Python :: 3
Classifier: Natural Language :: English
Classifier: Topic :: Scientific/Engineering :: Artificial Intelligence
Classifier: Intended Audience :: Science/Research
License-File: LICENSES/GPL-3.0-only.txt
Requires-Dist: keras
Requires-Dist: numpy
Requires-Dist: h5py
Requires-Dist: scipy
Requires-Dist: matplotlib
Requires-Dist: polars
Requires-Dist: pre-commit ; extra == "dev"
Requires-Dist: jax[cuda12] ; extra == "jax"
Requires-Dist: tensorflow[and-cuda] ; extra == "tensorflow"
Requires-Dist: torch ; extra == "torch"
Requires-Dist: torchvision ; extra == "torch"
Requires-Dist: torchaudio ; extra == "torch"
Project-URL: Source, https://github.com/idiap/RawSpeechClassification
Provides-Extra: dev
Provides-Extra: jax
Provides-Extra: tensorflow
Provides-Extra: torch
